bream/__init__.py
bream/coders.py
bream/core.py
bream/py.typed
bream-0.0.2.dist-info/METADATA
bream-0.0.2.dist-info/WHEEL
bream-0.0.2.dist-info/licenses/LICENSE
bream-0.0.2.dist-info/RECORD
