Metadata-Version: 2.4
Name: bream
Version: 0.0.2
Summary: Explicitly versioned JSON serialisation
Project-URL: Homepage, https://github.com/tpgillam/bream
Author-email: Tom Gillam <tpgillam@googlemail.com>
License: MIT License
License-File: LICENSE
Classifier: Development Status :: 2 - Pre-Alpha
Classifier: Intended Audience :: Developers
Classifier: License :: OSI Approved :: MIT License
Classifier: Natural Language :: English
Classifier: Programming Language :: Python :: 3
Classifier: Programming Language :: Python :: 3.12
Classifier: Programming Language :: Python :: 3.13
Requires-Python: >=3.12
